fastplasmon/__init__.py
fastplasmon/core.py
fastplasmon-0.1.dist-info/licenses/LICENSE
fastplasmon-0.1.dist-info/METADATA
fastplasmon-0.1.dist-info/WHEEL
fastplasmon-0.1.dist-info/top_level.txt
fastplasmon-0.1.dist-info/RECORD
