Metadata-Version: 2.4
Name: fastplasmon
Version: 0.1
Summary: Toolkit for fast computation of near and far-field quantities for plasmonic nanoparticles in the weakly retarded regime
Author-email: Paulo Santos <paulo.s.santos@inesctec.pt>
License: AGPLv3
Project-URL: Homepage, https://github.com/INESCTEC/fastplasmon
Project-URL: Bug Tracker, https://github.com/INESCTEC/fastplasmon/issues
Requires-Python: >=3.9
License-File: LICENSE
Requires-Dist: numpy>=1.26
Dynamic: license-file
